aatoolbox/__init__.py
aatoolbox/_version.py
aatoolbox/config/__init__.py
aatoolbox/config/countryconfig.py
aatoolbox/config/pathconfig.py
aatoolbox/config/countries/bfa.yaml
aatoolbox/config/countries/bgd.yaml
aatoolbox/config/countries/cod.yaml
aatoolbox/config/countries/eth.yaml
aatoolbox/config/countries/mwi.yaml
aatoolbox/config/countries/npl.yaml
aatoolbox/datasources/__init__.py
aatoolbox/datasources/datasource.py
aatoolbox/datasources/chirps/__init__.py
aatoolbox/datasources/chirps/chirps.py
aatoolbox/datasources/codab/__init__.py
aatoolbox/datasources/codab/codab.py
aatoolbox/datasources/fewsnet/__init__.py
aatoolbox/datasources/fewsnet/fewsnet.py
aatoolbox/datasources/glofas/__init__.py
aatoolbox/datasources/glofas/forecast.py
aatoolbox/datasources/glofas/glofas.py
aatoolbox/datasources/glofas/reanalysis.py
aatoolbox/datasources/iri/__init__.py
aatoolbox/datasources/iri/iri_seasonal_forecast.py
aatoolbox/datasources/usgs/__init__.py
aatoolbox/datasources/usgs/ndvi_base.py
aatoolbox/datasources/usgs/ndvi_products.py
aatoolbox/utils/__init__.py
aatoolbox/utils/check_file_existence.py
aatoolbox/utils/dates.py
aatoolbox/utils/geoboundingbox.py
aatoolbox/utils/hdx_api.py
aatoolbox/utils/io.py
aatoolbox/utils/raster.py
aa_toolbox-0.5.0.dist-info/LICENSE
aa_toolbox-0.5.0.dist-info/METADATA
aa_toolbox-0.5.0.dist-info/WHEEL
aa_toolbox-0.5.0.dist-info/top_level.txt
aa_toolbox-0.5.0.dist-info/RECORD
