Metadata-Version: 2.1
Name: aa-toolbox
Version: 0.5.0
Summary: Toolbox for anticipatory action
Home-page: https://github.com/OCHA-DAP/pa-aa-toolbox
Author: Centre for Humanitarian Data Predictive Analytics Team
Author-email: centrehumdata@un.org
License: GPLv3
Project-URL: Documentation, https://aa-toolbox.readthedocs.io/en/latest/
Project-URL: Changes, https://github.com/OCHA-DAP/pa-aa-toolbox/blob/main/CHANGELOG.rst
Project-URL: PyPI Releases, https://pypi.org/project/aa-toolbox/
Project-URL: Source Code, https://github.com/OCHA-DAP/pa-aa-toolbox/
Project-URL: Issue Tracker, https://github.com/OCHA-DAP/pa-aa-toolbox/issues/
Classifier: Development Status :: 3 - Alpha
Classifier: Intended Audience :: Developers
Classifier: License :: OSI Approved :: GNU General Public License v3 (GPLv3)
Classifier: Natural Language :: English
Classifier: Operating System :: OS Independent
Classifier: Programming Language :: Python :: 3 :: Only
Requires-Python: >=3.7
License-File: LICENSE
Requires-Dist: cdsapi
Requires-Dist: cfgrib
Requires-Dist: cftime
Requires-Dist: geopandas
Requires-Dist: hdx-python-api (>=5.6.4)
Requires-Dist: hdx-python-country
Requires-Dist: netCDF4
Requires-Dist: numpy
Requires-Dist: pydantic
Requires-Dist: python-dateutil
Requires-Dist: pyyaml
Requires-Dist: rasterio
Requires-Dist: requests
Requires-Dist: rioxarray
Requires-Dist: wrapt
Requires-Dist: xarray[parallel]
Requires-Dist: importlib-metadata (==4.13.0) ; python_version == "3.7"
